bioinformatics_tools/__init__.py
bioinformatics_tools/FileClasses/BAM.py
bioinformatics_tools/FileClasses/BaseClasses.py
bioinformatics_tools/FileClasses/BrowserExtensibleData.py
bioinformatics_tools/FileClasses/Fasta.py
bioinformatics_tools/FileClasses/Fastq.py
bioinformatics_tools/FileClasses/GeneTransferFormat.py
bioinformatics_tools/FileClasses/GeneralFeatureFormat.py
bioinformatics_tools/FileClasses/Generate.py
bioinformatics_tools/FileClasses/__init__.py
bioinformatics_tools/FileClasses/main.py
bioinformatics_tools/Utilities/__init__.py
bioinformatics_tools/Utilities/command_line.py
bioinformatics_tools/Utilities/shellOutput.py
bioinformatics_tools/Utilities/warnings.py
bioinformatics_tools/alignmentTools/__init__.py
bioinformatics_tools/alignmentTools/filterBamByReference.py
bioinformatics_tools/alignmentTools/samThresholdFilter.py
bioinformatics_tools/annotationTools/__init__.py
bioinformatics_tools/annotationTools/createVanillaGFF.py
bioinformatics_tools/annotationTools/genbankConverter.py
bioinformatics_tools/annotationTools/genbankToFasta.py
bioinformatics_tools/annotationTools/gff3TEST.py
bioinformatics_tools/annotationTools/gffMine.py
bioinformatics_tools/annotationTools/test.py
bioinformatics_tools/annotationTools/trimGFFByFeature.py
bioinformatics_tools/annotationTools/writeFlaggedContigsNewBinID.py
bioinformatics_tools/annotationTools/writeModeGFFFeaturePerBin.py
bioinformatics_tools/annotationTools/writeTaxonRemovedFastas.py
bioinformatics_tools/caragols/__init__.py
bioinformatics_tools/caragols/carp.py
bioinformatics_tools/caragols/clix.py
bioinformatics_tools/caragols/condo.py
bioinformatics_tools/caragols/config-caragols.yaml
bioinformatics_tools/caragols/configurator.py
bioinformatics_tools/caragols/logger.py
bioinformatics_tools/caragols/logging-config.json
bioinformatics_tools/fastaTools/FastaClasses.py
bioinformatics_tools/fastaTools/__init__.py
bioinformatics_tools/fastaTools/calcBinsetLengths.py
bioinformatics_tools-0.2.0.dist-info/licenses/LICENSE.txt
bioinformatics_tools-0.2.0.dist-info/METADATA
bioinformatics_tools-0.2.0.dist-info/WHEEL
bioinformatics_tools-0.2.0.dist-info/entry_points.txt
bioinformatics_tools-0.2.0.dist-info/top_level.txt
bioinformatics_tools-0.2.0.dist-info/RECORD
