Metadata-Version: 2.4
Name: bioinformatics_tools
Version: 0.2.0
Summary: Simple tools for common bioinformatic use-cases
Home-page: https://github.com/Diet-Microbiome-Interactions-Lab/GeneralTools
Author: Dane Deemer
Author-email: dane@liminalbios.com
Classifier: Programming Language :: Python :: 3
Classifier: License :: OSI Approved :: MIT License
Classifier: Operating System :: OS Independent
Requires-Python: >=3.11
License-File: LICENSE.txt
Requires-Dist: bio
Requires-Dist: matplotlib
Requires-Dist: numpy
Requires-Dist: pandas
Requires-Dist: pydantic==2.*
Requires-Dist: pydantic-sqlite==0.*
Requires-Dist: pyyaml==6.*
Requires-Dist: python-json-logger==2.0.7
Requires-Dist: typer
Dynamic: author
Dynamic: author-email
Dynamic: classifier
Dynamic: description
Dynamic: description-content-type
Dynamic: home-page
Dynamic: license-file
Dynamic: requires-dist
Dynamic: requires-python
Dynamic: summary
